sagesand/__init__.py
sagesand/feature_spider.py
sagesand/row_tagger.py
sagesand-0.1.1.dist-info/LICENSE
sagesand-0.1.1.dist-info/METADATA
sagesand-0.1.1.dist-info/WHEEL
sagesand-0.1.1.dist-info/top_level.txt
sagesand-0.1.1.dist-info/RECORD
