Metadata-Version: 2.1
Name: sagesand
Version: 0.1.1
Summary: SageMaker Sandbox
Home-page: https://github.com/SuperCowPowers/sagemaker_sandbox
Author: SuperCowPowers LLC
Author-email: support@supercowpowers.com
License: Apache License 2.0
Keywords: SageMaker,Machine Learning,AWS,Python,Utilities
Classifier: Development Status :: 2 - Pre-Alpha
Classifier: Intended Audience :: Developers
Classifier: License :: OSI Approved :: Apache Software License
Classifier: Natural Language :: English
Classifier: Programming Language :: Python :: 3.7
Classifier: Programming Language :: Python :: 3.8
Classifier: Programming Language :: Python :: 3.9
Classifier: Programming Language :: Python :: 3.10
Classifier: Programming Language :: Python :: Implementation :: CPython
Classifier: Programming Language :: Python :: Implementation :: PyPy
License-File: LICENSE
Requires-Dist: sagemaker
Requires-Dist: pandas
Requires-Dist: scikit-learn
